korona/__init__.py
korona/__pkg__.py
korona/html/__init__.py
korona/html/root/__init__.py
korona/html/root/attributes.py
korona/html/root/tags.py
korona/html/tags/__init__.py
korona/html/tags/abbreviate.py
korona/html/tags/acronym.py
korona/html/tags/address.py
korona/html/tags/anchor.py
korona/html/tags/area.py
korona/html/tags/article.py
korona/html/tags/base.py
korona/html/tags/bold.py
korona/html/tags/button.py
korona/html/tags/canvas.py
korona/html/tags/caption.py
korona/html/tags/cite.py
korona/html/tags/col.py
korona/html/tags/colgroup.py
korona/html/tags/delete.py
korona/html/tags/description.py
korona/html/tags/details.py
korona/html/tags/dialog.py
korona/html/tags/div.py
korona/html/tags/embed.py
korona/html/tags/fieldset.py
korona/html/tags/figure.py
korona/html/tags/footer.py
korona/html/tags/form.py
korona/html/tags/frame.py
korona/html/tags/frameset.py
korona/html/tags/head.py
korona/html/tags/header.py
korona/html/tags/heading.py
korona/html/tags/horizontal_rule.py
korona/html/tags/html.py
korona/html/tags/iframe.py
korona/html/tags/image.py
korona/html/tags/input.py
korona/html/tags/italics.py
korona/lib/__init__.py
korona/lib/utils.py
korona/templates/__init__.py
korona/templates/html/__init__.py
korona/templates/html/environment.py
korona/templates/html/tags/__init__.py
korona/templates/html/tags/abbreviate.py
korona/templates/html/tags/acronym.py
korona/templates/html/tags/address.py
korona/templates/html/tags/anchor.py
korona/templates/html/tags/area.py
korona/templates/html/tags/article.py
korona/templates/html/tags/base.py
korona/templates/html/tags/bold.py
korona/templates/html/tags/button.py
korona/templates/html/tags/canvas.py
korona/templates/html/tags/caption.py
korona/templates/html/tags/cite.py
korona/templates/html/tags/col.py
korona/templates/html/tags/colgroup.py
korona/templates/html/tags/delete.py
korona/templates/html/tags/description.py
korona-0.4.2.dist-info/DESCRIPTION.rst
korona-0.4.2.dist-info/METADATA
korona-0.4.2.dist-info/RECORD
korona-0.4.2.dist-info/WHEEL
korona-0.4.2.dist-info/metadata.json
korona-0.4.2.dist-info/top_level.txt
