Metadata-Version: 2.0
Name: korona
Version: 0.4.2
Summary: Package for building html pages
Home-page: https://github.com/bharadwajyarlagadda/korona
Author: Bharadwaj Yarlagadda
Author-email: yarlagaddabharadwaj@gmail.com
License: MIT License
Keywords: make html built html create html korona html maker html build
Platform: UNKNOWN
Classifier: Development Status :: 2 - Pre-Alpha
Classifier: Intended Audience :: Developers
Classifier: Operating System :: OS Independent
Classifier: Programming Language :: Python
Classifier: License :: OSI Approved :: MIT License
Classifier: Topic :: Software Development :: Libraries
Classifier: Topic :: Software Development :: Libraries :: Python Modules
Classifier: Programming Language :: Python
Classifier: Programming Language :: Python :: 2
Classifier: Programming Language :: Python :: 2.7
Classifier: Programming Language :: Python :: 3
Classifier: Programming Language :: Python :: 3.3
Classifier: Programming Language :: Python :: 3.4
Classifier: Programming Language :: Python :: 3.5
Requires-Dist: future (==0.15.2)
Requires-Dist: jinja2 (==2.8)
